Workbook

Sheet Inputs
A1: Retirement Planner Inputs
A3: Category | B3: Input | C3: Value | D3: Units | E3: Source URL
A4: Personal | B4: Current Age | C4: 35 | D4: years | E4: https://www.investor.gov/financial-tools-calculators/calculators/compound-interest-calculator
A5: Personal | B5: Retirement Age | C5: 65 | D5: years | E5: https://www.irs.gov/retirement-plans/plan-participant-employee/retirement-topics-catch-up-contributions
A6: Personal | B6: Life Expectancy | C6: 92 | D6: years | E6: https://www.ssa.gov/oact/STATS/table4c6.html
A7: Savings | B7: Current Retirement Savings | C7: 150000 | D7: $ | E7: https://www.fidelity.com/viewpoints/retirement/how-much-do-i-need-to-retire
A8: Savings | B8: Annual Contribution | C8: 18000 | D8: $/yr | E8: https://www.irs.gov/retirement-plans/plan-participant-employee/retirement-topics-ira-contribution-limits
A9: Savings | B9: Contribution Growth Rate | C9: 0.03 | D9: % | E9: https://www.bls.gov/cpi/
A10: Returns | B10: Pre-Retirement Return | C10: 0.065 | D10: % | E10: https://www.sec.gov/investor/alerts/ib_fees_expenses.pdf
A11: Returns | B11: Post-Retirement Return | C11: 0.045 | D11: % | E11: https://www.sec.gov/investor/alerts/ib_fees_expenses.pdf
A12: Spending | B12: Current Annual Spending | C12: 60000 | D12: $/yr | E12: https://www.bls.gov/cex/
A13: Spending | B13: Inflation Rate | C13: 0.025 | D13: % | E13: https://www.bls.gov/cpi/
A14: Income | B14: Expected Annual Social Security | C14: 30000 | D14: $/yr | E14: https://www.ssa.gov/benefits/retirement/planner/
A16: Derived
B17: Years to Retirement | C17: =C5-C4
B18: Years in Retirement | C18: =C6-C5

Sheet Projection
A1: Retirement Cash Flow Projection
A3: Year | B3: Age | C3: Start Balance ($) | D3: Contribution ($) | E3: Investment Return ($) | F3: Social Security ($) | G3: Spending Need ($) | H3: Net Cash Flow ($) | I3: End Balance ($) | J3: Status
A4: 1 | B4: =Inputs!$C$4+A4-1 | C4: =Inputs!$C$7 | D4: =IF(B4<Inputs!$C$5,Inputs!$C$8*(1+Inputs!$C$9)^(A4-1),0) | E4: =C4*IF(B4<Inputs!$C$5,Inputs!$C$10,Inputs!$C$11) | F4: =IF(B4>=Inputs!$C$5,Inputs!$C$14*(1+Inputs!$C$13)^(B4-Inputs!$C$5),0) | G4: =IF(B4>=Inputs!$C$5,Inputs!$C$12*(1+Inputs!$C$13)^(B4-Inputs!$C$5),0) | H4: =D4+E4+F4-G4 | I4: =MAX(0,C4+H4) | J4: =IF(B4>Inputs!$C$6,"",IF(I4=0,"Depleted","Funded"))
A5: 2 | B5: =Inputs!$C$4+A5-1 | C5: =I4 | D5: =IF(B5<Inputs!$C$5,Inputs!$C$8*(1+Inputs!$C$9)^(A5-1),0) | E5: =C5*IF(B5<Inputs!$C$5,Inputs!$C$10,Inputs!$C$11) | F5: =IF(B5>=Inputs!$C$5,Inputs!$C$14*(1+Inputs!$C$13)^(B5-Inputs!$C$5),0) | G5: =IF(B5>=Inputs!$C$5,Inputs!$C$12*(1+Inputs!$C$13)^(B5-Inputs!$C$5),0) | H5: =D5+E5+F5-G5 | I5: =MAX(0,C5+H5) | J5: =IF(B5>Inputs!$C$6,"",IF(I5=0,"Depleted","Funded"))
A6: 3 | B6: =Inputs!$C$4+A6-1 | C6: =I5 | D6: =IF(B6<Inputs!$C$5,Inputs!$C$8*(1+Inputs!$C$9)^(A6-1),0) | E6: =C6*IF(B6<Inputs!$C$5,Inputs!$C$10,Inputs!$C$11) | F6: =IF(B6>=Inputs!$C$5,Inputs!$C$14*(1+Inputs!$C$13)^(B6-Inputs!$C$5),0) | G6: =IF(B6>=Inputs!$C$5,Inputs!$C$12*(1+Inputs!$C$13)^(B6-Inputs!$C$5),0) | H6: =D6+E6+F6-G6 | I6: =MAX(0,C6+H6) | J6: =IF(B6>Inputs!$C$6,"",IF(I6=0,"Depleted","Funded"))
A7: 4 | B7: =Inputs!$C$4+A7-1 | C7: =I6 | D7: =IF(B7<Inputs!$C$5,Inputs!$C$8*(1+Inputs!$C$9)^(A7-1),0) | E7: =C7*IF(B7<Inputs!$C$5,Inputs!$C$10,Inputs!$C$11) | F7: =IF(B7>=Inputs!$C$5,Inputs!$C$14*(1+Inputs!$C$13)^(B7-Inputs!$C$5),0) | G7: =IF(B7>=Inputs!$C$5,Inputs!$C$12*(1+Inputs!$C$13)^(B7-Inputs!$C$5),0) | H7: =D7+E7+F7-G7 | I7: =MAX(0,C7+H7) | J7: =IF(B7>Inputs!$C$6,"",IF(I7=0,"Depleted","Funded"))
A8: 5 | B8: =Inputs!$C$4+A8-1 | C8: =I7 | D8: =IF(B8<Inputs!$C$5,Inputs!$C$8*(1+Inputs!$C$9)^(A8-1),0) | E8: =C8*IF(B8<Inputs!$C$5,Inputs!$C$10,Inputs!$C$11) | F8: =IF(B8>=Inputs!$C$5,Inputs!$C$14*(1+Inputs!$C$13)^(B8-Inputs!$C$5),0) | G8: =IF(B8>=Inputs!$C$5,Inputs!$C$12*(1+Inputs!$C$13)^(B8-Inputs!$C$5),0) | H8: =D8+E8+F8-G8 | I8: =MAX(0,C8+H8) | J8: =IF(B8>Inputs!$C$6,"",IF(I8=0,"Depleted","Funded"))
A9: 6 | B9: =Inputs!$C$4+A9-1 | C9: =I8 | D9: =IF(B9<Inputs!$C$5,Inputs!$C$8*(1+Inputs!$C$9)^(A9-1),0) | E9: =C9*IF(B9<Inputs!$C$5,Inputs!$C$10,Inputs!$C$11) | F9: =IF(B9>=Inputs!$C$5,Inputs!$C$14*(1+Inputs!$C$13)^(B9-Inputs!$C$5),0) | G9: =IF(B9>=Inputs!$C$5,Inputs!$C$12*(1+Inputs!$C$13)^(B9-Inputs!$C$5),0) | H9: =D9+E9+F9-G9 | I9: =MAX(0,C9+H9) | J9: =IF(B9>Inputs!$C$6,"",IF(I9=0,"Depleted","Funded"))
A10: 7 | B10: =Inputs!$C$4+A10-1 | C10: =I9 | D10: =IF(B10<Inputs!$C$5,Inputs!$C$8*(1+Inputs!$C$9)^(A10-1),0) | E10: =C10*IF(B10<Inputs!$C$5,Inputs!$C$10,Inputs!$C$11) | F10: =IF(B10>=Inputs!$C$5,Inputs!$C$14*(1+Inputs!$C$13)^(B10-Inputs!$C$5),0) | G10: =IF(B10>=Inputs!$C$5,Inputs!$C$12*(1+Inputs!$C$13)^(B10-Inputs!$C$5),0) | H10: =D10+E10+F10-G10 | I10: =MAX(0,C10+H10) | J10: =IF(B10>Inputs!$C$6,"",IF(I10=0,"Depleted","Funded"))
A11: 8 | B11: =Inputs!$C$4+A11-1 | C11: =I10 | D11: =IF(B11<Inputs!$C$5,Inputs!$C$8*(1+Inputs!$C$9)^(A11-1),0) | E11: =C11*IF(B11<Inputs!$C$5,Inputs!$C$10,Inputs!$C$11) | F11: =IF(B11>=Inputs!$C$5,Inputs!$C$14*(1+Inputs!$C$13)^(B11-Inputs!$C$5),0) | G11: =IF(B11>=Inputs!$C$5,Inputs!$C$12*(1+Inputs!$C$13)^(B11-Inputs!$C$5),0) | H11: =D11+E11+F11-G11 | I11: =MAX(0,C11+H11) | J11: =IF(B11>Inputs!$C$6,"",IF(I11=0,"Depleted","Funded"))
A12: 9 | B12: =Inputs!$C$4+A12-1 | C12: =I11 | D12: =IF(B12<Inputs!$C$5,Inputs!$C$8*(1+Inputs!$C$9)^(A12-1),0) | E12: =C12*IF(B12<Inputs!$C$5,Inputs!$C$10,Inputs!$C$11) | F12: =IF(B12>=Inputs!$C$5,Inputs!$C$14*(1+Inputs!$C$13)^(B12-Inputs!$C$5),0) | G12: =IF(B12>=Inputs!$C$5,Inputs!$C$12*(1+Inputs!$C$13)^(B12-Inputs!$C$5),0) | H12: =D12+E12+F12-G12 | I12: =MAX(0,C12+H12) | J12: =IF(B12>Inputs!$C$6,"",IF(I12=0,"Depleted","Funded"))
A13: 10 | B13: =Inputs!$C$4+A13-1 | C13: =I12 | D13: =IF(B13<Inputs!$C$5,Inputs!$C$8*(1+Inputs!$C$9)^(A13-1),0) | E13: =C13*IF(B13<Inputs!$C$5,Inputs!$C$10,Inputs!$C$11) | F13: =IF(B13>=Inputs!$C$5,Inputs!$C$14*(1+Inputs!$C$13)^(B13-Inputs!$C$5),0) | G13: =IF(B13>=Inputs!$C$5,Inputs!$C$12*(1+Inputs!$C$13)^(B13-Inputs!$C$5),0) | H13: =D13+E13+F13-G13 | I13: =MAX(0,C13+H13) | J13: =IF(B13>Inputs!$C$6,"",IF(I13=0,"Depleted","Funded"))
A14: 11 | B14: =Inputs!$C$4+A14-1 | C14: =I13 | D14: =IF(B14<Inputs!$C$5,Inputs!$C$8*(1+Inputs!$C$9)^(A14-1),0) | E14: =C14*IF(B14<Inputs!$C$5,Inputs!$C$10,Inputs!$C$11) | F14: =IF(B14>=Inputs!$C$5,Inputs!$C$14*(1+Inputs!$C$13)^(B14-Inputs!$C$5),0) | G14: =IF(B14>=Inputs!$C$5,Inputs!$C$12*(1+Inputs!$C$13)^(B14-Inputs!$C$5),0) | H14: =D14+E14+F14-G14 | I14: =MAX(0,C14+H14) | J14: =IF(B14>Inputs!$C$6,"",IF(I14=0,"Depleted","Funded"))
A15: 12 | B15: =Inputs!$C$4+A15-1 | C15: =I14 | D15: =IF(B15<Inputs!$C$5,Inputs!$C$8*(1+Inputs!$C$9)^(A15-1),0) | E15: =C15*IF(B15<Inputs!$C$5,Inputs!$C$10,Inputs!$C$11) | F15: =IF(B15>=Inputs!$C$5,Inputs!$C$14*(1+Inputs!$C$13)^(B15-Inputs!$C$5),0) | G15: =IF(B15>=Inputs!$C$5,Inputs!$C$12*(1+Inputs!$C$13)^(B15-Inputs!$C$5),0) | H15: =D15+E15+F15-G15 | I15: =MAX(0,C15+H15) | J15: =IF(B15>Inputs!$C$6,"",IF(I15=0,"Depleted","Funded"))
A16: 13 | B16: =Inputs!$C$4+A16-1 | C16: =I15 | D16: =IF(B16<Inputs!$C$5,Inputs!$C$8*(1+Inputs!$C$9)^(A16-1),0) | E16: =C16*IF(B16<Inputs!$C$5,Inputs!$C$10,Inputs!$C$11) | F16: =IF(B16>=Inputs!$C$5,Inputs!$C$14*(1+Inputs!$C$13)^(B16-Inputs!$C$5),0) | G16: =IF(B16>=Inputs!$C$5,Inputs!$C$12*(1+Inputs!$C$13)^(B16-Inputs!$C$5),0) | H16: =D16+E16+F16-G16 | I16: =MAX(0,C16+H16) | J16: =IF(B16>Inputs!$C$6,"",IF(I16=0,"Depleted","Funded"))
... A73: 70 | B73: =Inputs!$C$4+A73-1 | C73: =I72 | D73: =IF(B73<Inputs!$C$5,Inputs!$C$8*(1+Inputs!$C$9)^(A73-1),0) | E73: =C73*IF(B73<Inputs!$C$5,Inputs!$C$10,Inputs!$C$11) | F73: =IF(B73>=Inputs!$C$5,Inputs!$C$14*(1+Inputs!$C$13)^(B73-Inputs!$C$5),0) | G73: =IF(B73>=Inputs!$C$5,Inputs!$C$12*(1+Inputs!$C$13)^(B73-Inputs!$C$5),0) | H73: =D73+E73+F73-G73 | I73: =MAX(0,C73+H73) | J73: =IF(B73>Inputs!$C$6,"",IF(I73=0,"Depleted","Funded"))

Sheet Summary
A1: Retirement Summary
A3: Metric | B3: Value
A4: Projected Balance at Retirement ($) | B4: =INDEX(Projection!I:I, MATCH(Inputs!$C$5, Projection!B:B, 0))
A5: Final Balance at Life Expectancy ($) | B5: =INDEX(Projection!I:I, MATCH(Inputs!$C$6, Projection!B:B, 0))
A6: First Depletion Age | B6: =IFERROR(INDEX(Projection!B:B,MATCH("Depleted",Projection!J:J,0)),"Not Depleted")
A7: Retirement Spending in First Year ($) | B7: =INDEX(Projection!G:G, MATCH(Inputs!$C$5, Projection!B:B, 0))
A8: Estimated Income Gap at Retirement ($) | B8: =INDEX(Projection!G:G, MATCH(Inputs!$C$5, Projection!B:B, 0))-INDEX(Projection!F:F, MATCH(Inputs!$C$5, Projection!B:B, 0))
A10: Plan Health | B10: =IF(B6="Not Depleted","On Track",IF(B6>Inputs!$C$6,"On Track","Needs Adjustment"))
